<?xml version="1.0" encoding="UTF-8"?><?xml-stylesheet type='text/xsl' href='_UpgradeReport_Files/UpgradeReport.xslt'?><UpgradeLog>
<Properties><Property Name="Solution" Value="Community Core Vision">
</Property><Property Name="Solution File" Value="C:\_WORK\vs2010port\ccv15\apps\addonsExamples\VS2010\Community Core Vision.sln">
</Property><Property Name="User Options File" Value="C:\_WORK\vs2010port\ccv15\apps\addonsExamples\VS2010\Community Core Vision.suo">
</Property><Property Name="Date" Value="5 сентября 2012 г.">
</Property><Property Name="Time" Value="10:48">
</Property></Properties><Event ErrorLevel="0" Project="" Source="Community Core Vision.sln" Description="File successfully backed up as C:\_WORK\vs2010port\ccv15\apps\addonsExamples\VS2010\Community Core Vision.sln.old">
</Event><Event ErrorLevel="0" Project="" Source="Community Core Vision.suo" Description="File successfully backed up as C:\_WORK\vs2010port\ccv15\apps\addonsExamples\VS2010\Community Core Vision.suo.old">
</Event><Event ErrorLevel="0" Project="Community Core Vision" Source="Community Core Vision.vcproj" Description="Converting project file 'C:\_WORK\vs2010port\ccv15\apps\addonsExamples\VS2010\Community Core Vision.vcproj'.">
</Event><Event ErrorLevel="1" Project="Community Core Vision" Source="Community Core Vision.vcproj" Description="VCWebServiceProxyGeneratorTool is no longer supported. The tool has been removed from your project settings.">
</Event><Event ErrorLevel="1" Project="Community Core Vision" Source="Community Core Vision.vcproj" Description="Attribute 'Detect64BitPortabilityProblems' of 'VCCLCompilerTool' is not supported in this version and has been removed during conversion.">
</Event><Event ErrorLevel="1" Project="Community Core Vision" Source="Community Core Vision.vcproj" Description="Attribute 'Detect64BitPortabilityProblems' of 'VCCLCompilerTool' is not supported in this version and has been removed during conversion.">
</Event><Event ErrorLevel="1" Project="Community Core Vision" Source="Community Core Vision.vcproj" Description="MSB8012: $(TargetName) ('Community Core Vision') does not match the Linker's OutputFile property value 'bin\CCV_debug.exe' ('CCV_debug') in project configuration 'Debug|Win32'. This may cause your project to build incorrectly. To correct this, please make sure that $(TargetName) property value matches the value specified in %(Link.OutputFile).">
</Event><Event ErrorLevel="1" Project="Community Core Vision" Source="Community Core Vision.vcproj" Description="MSB8012: $(TargetPath) ('C:\_WORK\vs2010port\ccv15\apps\addonsExamples\VS2010\bin\Community Core Vision.exe') does not match the Linker's OutputFile property value 'bin\CCV_debug.exe' ('C:\_WORK\vs2010port\ccv15\apps\addonsExamples\VS2010\bin\CCV_debug.exe') in project configuration 'Debug|Win32'. This may cause your project to build incorrectly. To correct this, please make sure that $(TargetPath) property value matches the value specified in %(Link.OutputFile).">
</Event><Event ErrorLevel="1" Project="Community Core Vision" Source="Community Core Vision.vcproj" Description="MSB8012: $(TargetName) ('Community Core Vision') does not match the Linker's OutputFile property value 'bin\CCV.exe' ('CCV') in project configuration 'Release|Win32'. This may cause your project to build incorrectly. To correct this, please make sure that $(TargetName) property value matches the value specified in %(Link.OutputFile).">
</Event><Event ErrorLevel="1" Project="Community Core Vision" Source="Community Core Vision.vcproj" Description="MSB8012: $(TargetPath) ('C:\_WORK\vs2010port\ccv15\apps\addonsExamples\VS2010\bin\Community Core Vision.exe') does not match the Linker's OutputFile property value 'bin\CCV.exe' ('C:\_WORK\vs2010port\ccv15\apps\addonsExamples\VS2010\bin\CCV.exe') in project configuration 'Release|Win32'. This may cause your project to build incorrectly. To correct this, please make sure that $(TargetPath) property value matches the value specified in %(Link.OutputFile).">
</Event><Event ErrorLevel="0" Project="Community Core Vision" Source="Community Core Vision.vcproj" Description="Done converting to new project file 'C:\_WORK\vs2010port\ccv15\apps\addonsExamples\VS2010\Community Core Vision.vcxproj'.">
</Event><Event ErrorLevel="3" Project="Community Core Vision" Source="Community Core Vision.vcproj" Description="Converted">
</Event><Event ErrorLevel="0" Project="" Source="Community Core Vision.sln" Description="Solution converted successfully">
</Event><Event ErrorLevel="3" Project="" Source="Community Core Vision.sln" Description="Converted">
</Event></UpgradeLog>